{"cookies": [{"name": "SERVERID", "value": "w10", "domain": "www.sportslottery.com.tw", "path": "/", "expires": -1, "httpOnly": false, "secure": false, "sameSite": "Lax"}, {"name": "language", "value": "ZH", "domain": "www.sportslottery.com.tw", "path": "/", "expires": -1, "httpOnly": false, "secure": false, "sameSite": "Lax"}, {"name": "i18next", "value": "zh", "domain": "www.sportslottery.com.tw", "path": "/", "expires": -1, "httpOnly": false, "secure": false, "sameSite": "Lax"}, {"name": "cf_clearance", "value": "MW89P0NMpGFe.WpkrouOV.ZuUcNAzx9pvLIKaL.fVLE-1780808891-1.2.1.1-iRlJjFuG2MLy5JiqvyMHurRbPXQDMynScUsiLWTZYWsH1kSTAtv3ZgQEfyaBzFm7zppgmALNPAYGYd2JFCEq6LvagtE0jMa8O4hPiMgSIoWx7Ozinve6zQlUetgkJpKBca7dyqVSr8wX5f.muucmV4fCSrAodEsLeawBny4uL13AiQLTGH1PsRvc2j5WNCqlmMZDXhpZiLyRg3o_HvHKcN1TwC7sXbfS6pupQLfQdaWT8NTpax0cwYuoIabTOqQppEtwRfvVHRzpwC0eXOV0djn_ygsemKMYSEvhxAkNE1Wk6jjEyiRnS0UTJIQPQOXRKWCtDZVoDeyXJTrHVWJfmA", "domain": ".sportslottery.com.tw", "path": "/", "expires": 1812344889.79091, "httpOnly": true, "secure": true, "sameSite": "None", "partitionKey": "https://sportslottery.com.tw", "_crHasCrossSiteAncestor": false}, {"name": "SERVERID", "value": "w5", "domain": "www-talo-ssb-pr.sportslottery.com.tw", "path": "/", "expires": -1, "httpOnly": false, "secure": false, "sameSite": "Lax"}, {"name": "POSNODEID", "value": "n06", "domain": ".sportslottery.com.tw", "path": "/", "expires": -1, "httpOnly": false, "secure": false, "sameSite": "Lax"}, {"name": "_ga", "value": "GA1.1.420904823.1780808890", "domain": ".sportslottery.com.tw", "path": "/", "expires": 1815368889.901627, "httpOnly": false, "secure": false, "sameSite": "Lax"}, {"name": "essentialCookie", "value": "true", "domain": "www.sportslottery.com.tw", "path": "/", "expires": 1812365821.482495, "httpOnly": false, "secure": false, "sameSite": "Lax"}, {"name": "advertisingCookie", "value": "true", "domain": "www.sportslottery.com.tw", "path": "/", "expires": 1812365821.484118, "httpOnly": false, "secure": false, "sameSite": "Lax"}, {"name": "analyticsCustomizationCookie", "value": "true", "domain": "www.sportslottery.com.tw", "path": "/", "expires": 1812365821.484365, "httpOnly": false, "secure": false, "sameSite": "Lax"}, {"name": "performanceFunctionalityCookie", "value": "true", "domain": "www.sportslottery.com.tw", "path": "/", "expires": 1812365821.484581, "httpOnly": false, "secure": false, "sameSite": "Lax"}, {"name": "SERVERID", "value": "s2", "domain": "cdn1-talo-ssb-pr.sportslottery.com.tw", "path": "/", "expires": -1, "httpOnly": false, "secure": false, "sameSite": "Lax"}, {"name": "_ga_JV0N3L61WG", "value": "GS2.1.s1780808889$o1$g1$t1780808950$j60$l0$h0", "domain": ".sportslottery.com.tw", "path": "/", "expires": 1815368950.243889, "httpOnly": false, "secure": false, "sameSite": "Lax"}, {"name": "_ga_NYPMKHSD7X", "value": "GS2.1.s1780808891$o1$g1$t1780808950$j1$l0$h0", "domain": ".sportslottery.com.tw", "path": "/", "expires": 1815368950.438577, "httpOnly": false, "secure": false, "sameSite": "Lax"}], "origins": [{"origin": "https://www.sportslottery.com.tw", "localStorage": [{"name": "persist:LottoBetslipReducer", "value": "{\"line\":\"null\",\"_persist\":\"{\\\"version\\\":-1,\\\"rehydrated\\\":true}\"}"}, {"name": "persist:betSlip", "value": "{\"selection\":\"[]\",\"betTypes\":\"[]\",\"editMode\":\"[]\",\"totalStake\":\"0\",\"totalStakeWithTaxes\":\"0\",\"betTypesByID\":\"{}\",\"calculatedBets\":\"{}\",\"stakedElements\":\"{}\",\"status\":\"\\\"betslip\\\"\",\"betslipObjectStatus\":\"[]\",\"disclaimerVisibility\":\"true\",\"externalPlaceBet\":\"\\\"\\\"\",\"externalConfirmBet\":\"\\\"\\\"\",\"freebetToggle\":\"false\",\"retainSelectionToggle\":\"false\",\"loading\":\"false\",\"betCode\":\"null\",\"visible\":\"\\\"desktop\\\"\",\"selectedSection\":\"\\\"BETSLIP\\\"\",\"betBuilderBets\":\"{}\",\"extendedInfo\":\"{}\",\"_persist\":\"{\\\"version\\\":-1,\\\"rehydrated\\\":true}\"}"}, {"name": "language", "value": "zh"}]}, {"origin": "https://www-talo-ssb-pr.sportslottery.com.tw", "localStorage": [{"name": "persist:LottoBetslipReducer", "value": "{\"line\":\"null\",\"_persist\":\"{\\\"version\\\":-1,\\\"rehydrated\\\":true}\"}"}, {"name": "persist:betSlip", "value": "{\"selection\":\"[]\",\"betTypes\":\"[]\",\"editMode\":\"[]\",\"totalStake\":\"0\",\"totalStakeWithTaxes\":\"0\",\"betTypesByID\":\"{}\",\"calculatedBets\":\"{}\",\"stakedElements\":\"{}\",\"status\":\"\\\"betslip\\\"\",\"betTypeSelected\":\"\\\"Singles\\\"\",\"betslipObjectStatus\":\"[]\",\"disclaimerVisibility\":\"true\",\"externalPlaceBet\":\"\\\"\\\"\",\"externalConfirmBet\":\"\\\"\\\"\",\"freebetToggle\":\"false\",\"retainSelectionToggle\":\"false\",\"loading\":\"false\",\"betCode\":\"null\",\"visible\":\"\\\"desktop\\\"\",\"selectedSection\":\"\\\"BETSLIP\\\"\",\"betBuilderBets\":\"{}\",\"extendedInfo\":\"{}\",\"_persist\":\"{\\\"version\\\":-1,\\\"rehydrated\\\":true}\"}"}, {"name": "SIR_license", "value": "{\"value\":{\"sample\":0.397},\"timestamp\":false}"}, {"name": "language", "value": "zh"}]}]}